guitarpro/__init__.py
guitarpro/gp3.py
guitarpro/gp4.py
guitarpro/gp5.py
guitarpro/io.py
guitarpro/iobase.py
guitarpro/models.py
guitarpro/utils.py
pyguitarpro-0.10.1.dist-info/licenses/LICENSE
pyguitarpro-0.10.1.dist-info/WHEEL
pyguitarpro-0.10.1.dist-info/METADATA
pyguitarpro-0.10.1.dist-info/RECORD
