Metadata-Version: 2.4
Name: pyguitarpro
Version: 0.10.1
Summary: Read, write, and manipulate GP3, GP4 and GP5 files.
Author: Sviatoslav Abakumov
Author-email: Sviatoslav Abakumov <dust.harvesting@gmail.com>
License-Expression: LGPL-3.0-only
License-File: LICENSE
Classifier: Development Status :: 4 - Beta
Classifier: License :: OSI Approved :: GNU Lesser General Public License v3 (LGPLv3)
Classifier: Programming Language :: Python :: 3
Classifier: Programming Language :: Python :: 3 :: Only
Classifier: Programming Language :: Python :: 3.9
Classifier: Programming Language :: Python :: 3.10
Classifier: Programming Language :: Python :: 3.11
Classifier: Programming Language :: Python :: 3.12
Classifier: Programming Language :: Python :: 3.13
Classifier: Programming Language :: Python :: 3.14
Classifier: Programming Language :: Python :: Implementation :: CPython
Classifier: Programming Language :: Python :: Implementation :: PyPy
Classifier: Topic :: Artistic Software
Classifier: Topic :: Multimedia :: Sound/Audio
Requires-Dist: attrs>=19.2
Requires-Python: >=3.9
Project-URL: Documentation, https://pyguitarpro.readthedocs.io/
Project-URL: Issue tracker, https://github.com/Perlence/PyGuitarPro/issues
Project-URL: Source code, https://github.com/Perlence/PyGuitarPro
